{"ref":"2Ch.32.29","book":"2CH","chapter":"32","verse":"29","testament":"OT","words":[{"original":"וְ/עָרִים֙","translit":"ve./'a.Rim","strongs":"H9002/{H5892B}","morph":"HC/Ncmpa","gloss":"and/ cities"},{"original":"עָ֣שָׂה","translit":"'A.sah","strongs":"{H6213H}","morph":"HVqp3ms","gloss":"he made"},{"original":"ל֔/וֹ","translit":"l/o","strongs":"H9005/{H9033}","morph":"HR/Sp3ms","gloss":"for/ himself"},{"original":"וּ/מִקְנֵה\\־","translit":"u./mik.neh-","strongs":"H9002/{H4735}\\H9014","morph":"HC/Ncmsc","gloss":"and/ livestock of"},{"original":"צֹ֥אן","translit":"tzon","strongs":"{H6629G}","morph":"HNcbsa","gloss":"flock"},{"original":"וּ/בָקָ֖ר","translit":"u./va.Kar","strongs":"H9002/{H1241}","morph":"HC/Ncbsa","gloss":"and/ herd"},{"original":"לָ/רֹ֑ב","translit":"la./Ro","strongs":"H9005/{H7230}","morph":"HR/Ncmsa","gloss":"to/ abundance"},{"original":"כִּ֤י","translit":"ki","strongs":"{H3588A}","morph":"HTc","gloss":"for"},{"original":"נָֽתַן\\־","translit":"na.tan-","strongs":"{H5414G}\\H9014","morph":"HVqp3ms","gloss":"he had given"},{"original":"ל/וֹ֙","translit":"l/o","strongs":"H9005/{H9033}","morph":"HR/Sp3ms","gloss":"to/ him"},{"original":"אֱלֹהִ֔ים","translit":"'E.lo.Him","strongs":"{H0430G}","morph":"HNcmpa","gloss":"God"},{"original":"רְכ֖וּשׁ","translit":"re.Khush","strongs":"{H7399}","morph":"HNcmsa","gloss":"property"},{"original":"רַ֥ב","translit":"rav","strongs":"{H7227A}","morph":"HAamsa","gloss":"much"},{"original":"מְאֹֽד\\׃","translit":"me.'Od","strongs":"{H3966}\\H9016","morph":"HAcmsa","gloss":"very"}]}