{"ref":"Rev.18.13","book":"REV","chapter":"18","verse":"13","testament":"NT","words":[{"original":"καὶ","translit":"kai","strongs":"G2532","morph":"CONJ","gloss":"and"},{"original":"κιννάμωμον","translit":"kinnamōmon","strongs":"G2792","morph":"N-ASN","gloss":"cinnamon"},{"original":"καὶ","translit":"kai","strongs":"G2532","morph":"CONJ","gloss":"and"},{"original":"ἄμωμον","translit":"amōmon","strongs":"G6007","morph":"N-ASN","gloss":"spice"},{"original":"καὶ","translit":"kai","strongs":"G2532","morph":"CONJ","gloss":"and"},{"original":"θυμιάματα","translit":"thumiamata","strongs":"G2368","morph":"N-APN","gloss":"incense"},{"original":"καὶ","translit":"kai","strongs":"G2532","morph":"CONJ","gloss":"and"},{"original":"μύρον","translit":"muron","strongs":"G3464","morph":"N-ASN","gloss":"myrrh"},{"original":"καὶ","translit":"kai","strongs":"G2532","morph":"CONJ","gloss":"and"},{"original":"λίβανον","translit":"libanon","strongs":"G3030","morph":"N-ASM","gloss":"frankincense"},{"original":"καὶ","translit":"kai","strongs":"G2532","morph":"CONJ","gloss":"and"},{"original":"οἶνον","translit":"oinon","strongs":"G3631","morph":"N-ASM","gloss":"wine"},{"original":"καὶ","translit":"kai","strongs":"G2532","morph":"CONJ","gloss":"and"},{"original":"ἔλαιον","translit":"elaion","strongs":"G1637","morph":"N-ASN","gloss":"oil"},{"original":"καὶ","translit":"kai","strongs":"G2532","morph":"CONJ","gloss":"and"},{"original":"σεμίδαλιν","translit":"semidalin","strongs":"G4585","morph":"N-ASF","gloss":"finest flour"},{"original":"καὶ","translit":"kai","strongs":"G2532","morph":"CONJ","gloss":"and"},{"original":"σῖτον","translit":"siton","strongs":"G4621","morph":"N-ASM","gloss":"wheat"},{"original":"καὶ","translit":"kai","strongs":"G2532","morph":"CONJ","gloss":"and"},{"original":"κτήνη","translit":"ktēnē","strongs":"G2934","morph":"N-APN","gloss":"cattle"},{"original":"καὶ","translit":"kai","strongs":"G2532","morph":"CONJ","gloss":"and"},{"original":"πρόβατα","translit":"probata","strongs":"G4263","morph":"N-APN","gloss":"sheep"},{"original":"καὶ","translit":"kai","strongs":"G2532","morph":"CONJ","gloss":"and"},{"original":"ἵππων","translit":"ippōn","strongs":"G2462","morph":"N-GPM","gloss":"of horses"},{"original":"καὶ","translit":"kai","strongs":"G2532","morph":"CONJ","gloss":"and"},{"original":"ῥεδῶν","translit":"rhedōn","strongs":"G4480","morph":"N-GPF","gloss":"of chariots"},{"original":"καὶ","translit":"kai","strongs":"G2532","morph":"CONJ","gloss":"and"},{"original":"σωμάτων","translit":"sōmatōn","strongs":"G4983","morph":"N-GPN","gloss":"of slaves"},{"original":"καὶ","translit":"kai","strongs":"G2532","morph":"CONJ","gloss":"and"},{"original":"ψυχὰς","translit":"psuchas","strongs":"G5590J","morph":"N-APF","gloss":"souls"},{"original":"ἀνθρώπων.","translit":"anthrōpōn","strongs":"G0444","morph":"N-GPM","gloss":"of men."}]}