{"ref":"Num.34.15","book":"NUM","chapter":"34","verse":"15","testament":"OT","words":[{"original":"שְׁנֵ֥י","translit":"she.Nei","strongs":"{H8147}","morph":"HAcbdc","gloss":"[the] two"},{"original":"הַ/מַּטּ֖וֹת","translit":"ha./ma.Tot","strongs":"H9009/{H4294H}","morph":"HTd/Ncfpa","gloss":"the/ tribes"},{"original":"וַ/חֲצִ֣י","translit":"va./cha.Tzi","strongs":"H9002/{H2677}","morph":"HC/Ncmsc","gloss":"and/ [the] half of"},{"original":"הַ/מַּטֶּ֑ה","translit":"ha./ma.Teh","strongs":"H9009/{H4294H}","morph":"HTd/Ncmsa","gloss":"the/ tribe"},{"original":"לָקְח֣וּ","translit":"la.ke.Chu","strongs":"{H3947H}","morph":"HVqp3cp","gloss":"they have taken"},{"original":"נַחֲלָתָ֗/ם","translit":"na.cha.la.Ta/m","strongs":"{H5159}/H9028","morph":"HNcfsc/Sp3mp","gloss":"inheritance/ their"},{"original":"מֵ/עֵ֛בֶר","translit":"me./'E.ver","strongs":"H9006/{H5676H}","morph":"HR/Ncmsc","gloss":"from/ [the] other side"},{"original":"לְ/יַרְדֵּ֥ן","translit":"le./yar.Den","strongs":"H9005/{H3383}","morph":"HR/Npl","gloss":"of/ [the] Jordan"},{"original":"יְרֵח֖וֹ","translit":"ye.re.Cho","strongs":"{H3405G}","morph":"HNpl","gloss":"of Jericho"},{"original":"קֵ֥דְמָ/ה","translit":"Ke.de.ma/h","strongs":"{H6924B}/H9011","morph":"HNcmsa/Sd","gloss":"east/ -ward"},{"original":"מִזְרָֽחָ/ה\\׃\\ \\פ","translit":"miz.Ra.cha/h","strongs":"{H4217H}/H9011\\H9016\\ \\H9017","morph":"HNcmsa/Sd","gloss":"east/ -ward"}]}