{"ref":"Job.31.22","book":"JOB","chapter":"31","verse":"22","testament":"OT","words":[{"original":"כְּ֭תֵפִ/י","translit":"Ke.te.f/i","strongs":"{H3802}/H9020","morph":"HNcfsc/Sp1bs","gloss":"shoulder/ my"},{"original":"מִ/שִּׁכְמָ֣/ה","translit":"mi./shikh.Ma/h","strongs":"H9006/{H7929}/H9011","morph":"HR/Ncmsc/Sd","gloss":"from/ its shoulder/ <towards>"},{"original":"תִפּ֑וֹל","translit":"ti.Pol","strongs":"{H5307G}","morph":"HVqi3fs","gloss":"let it fall"},{"original":"וְ֝/אֶזְרֹעִ֗/י","translit":"ve./'ez.ro.'/I","strongs":"H9002/{H0248}/H9020","morph":"HC/Ncfsc/Sp1bs","gloss":"and/ arm/ my"},{"original":"מִ/קָּנָ֥/ה","translit":"mi./ka.Na/h","strongs":"H9006/{H7070J}/H9024","morph":"HR/Ncmsc/Sp3fs","gloss":"from/ arm/ its"},{"original":"תִשָּׁבֵֽר\\׃","translit":"ti.sha.Ver","strongs":"{H7665}\\H9016","morph":"HVNi3fs","gloss":"let it be broken"}]}