{"ref":"1Ti.4.13","book":"1TI","chapter":"4","verse":"13","testament":"NT","words":[{"original":"ἕως","translit":"he'ōs","strongs":"G2193","morph":"PREP","gloss":"Until"},{"original":"ἔρχομαι,","translit":"erchomai","strongs":"G2064","morph":"V-PNI-1S","gloss":"I come,"},{"original":"πρόσεχε","translit":"proseche","strongs":"G4337","morph":"V-PAM-2S","gloss":"do give heed"},{"original":"τῇ","translit":"tēa","strongs":"G3588","morph":"T-DSF","gloss":"to the"},{"original":"ἀναγνώσει,","translit":"anagnōsei","strongs":"G0320","morph":"N-DSF","gloss":"public reading of Scripture,"},{"original":"τῇ","translit":"tēa","strongs":"G3588","morph":"T-DSF","gloss":"<the>"},{"original":"παρακλήσει,","translit":"paraklēsei","strongs":"G3874","morph":"N-DSF","gloss":"to exhortation,"},{"original":"τῇ","translit":"tēa","strongs":"G3588","morph":"T-DSF","gloss":"<the>"},{"original":"διδασκαλίᾳ,","translit":"didaskalia","strongs":"G1319","morph":"N-DSF","gloss":"to teaching,"}]}