{"ref":"Pro.17.1","book":"PRO","chapter":"17","verse":"1","testament":"OT","words":[{"original":"ט֤וֹב","translit":"Tov","strongs":"{H2896A}","morph":"HAamsa","gloss":"[is] good"},{"original":"פַּ֣ת","translit":"pat","strongs":"{H6595A}","morph":"HNcfsa","gloss":"a morsel"},{"original":"חֲ֭רֵבָה","translit":"Cha.re.vah","strongs":"{H2720A}","morph":"HAafsa","gloss":"dry"},{"original":"וְ/שַׁלְוָה\\־","translit":"ve./shal.vah-","strongs":"H9002/{H7962}\\H9014","morph":"HC/Ncfsa","gloss":"and/ quietness"},{"original":"בָ֑/הּ","translit":"Va/h","strongs":"H9003/{H9034}","morph":"HR/Sp3fs","gloss":"with/ it"},{"original":"מִ֝/בַּ֗יִת","translit":"mi./Ba.yit","strongs":"H9006/{H1004B}","morph":"HR/Ncmsa","gloss":"more than/ a house"},{"original":"מָלֵ֥א","translit":"ma.Le'","strongs":"{H4392}","morph":"HAamsa","gloss":"full"},{"original":"זִבְחֵי\\־","translit":"ziv.chei-","strongs":"{H2077}\\H9014","morph":"HNcmpc","gloss":"sacrifices of"},{"original":"רִֽיב\\׃","translit":"Riv","strongs":"{H7379}\\H9016","morph":"HNcmsa","gloss":"strife"}]}