{"ref":"2Ki.3.4","book":"2KI","chapter":"3","verse":"4","testament":"OT","words":[{"original":"וּ/מֵישַׁ֥ע","translit":"u./mei.Sha'","strongs":"H9002/{H4338}","morph":"HC/Npm","gloss":"and/ Mesha"},{"original":"מֶֽלֶךְ\\־","translit":"Me.lekh-","strongs":"{H4428G}\\H9014","morph":"HNcmsc","gloss":"[the] king of"},{"original":"מוֹאָ֖ב","translit":"mo.'Av","strongs":"{H4124G}","morph":"HNpl","gloss":"Moab"},{"original":"הָיָ֣ה","translit":"ha.Yah","strongs":"{H1961}","morph":"HVqp3ms","gloss":"he was"},{"original":"נֹקֵ֑ד","translit":"no.Ked","strongs":"{H5349}","morph":"HNcmsa","gloss":"a sheep-breeder"},{"original":"וְ/הֵשִׁ֤יב","translit":"ve./he.Shiv","strongs":"H9001/{H7725G}","morph":"Hc/Vhq3ms","gloss":"and/ he returned"},{"original":"לְ/מֶֽלֶךְ\\־","translit":"le./Me.lekh-","strongs":"H9005/{H4428G}\\H9014","morph":"HR/Ncmsc","gloss":"to/ [the] king of"},{"original":"יִשְׂרָאֵל֙","translit":"Yis.ra.'El","strongs":"{H3478}","morph":"HNpl","gloss":"Israel"},{"original":"מֵאָה\\־","translit":"me.'ah-","strongs":"{H3967}\\H9014","morph":"HNcfsa","gloss":"one hundred"},{"original":"אֶ֣לֶף","translit":"'E.lef","strongs":"{H0505G}","morph":"HNcbsa","gloss":"thousand"},{"original":"כָּרִ֔ים","translit":"ka.Rim","strongs":"{H3733C}","morph":"HNcmpa","gloss":"lambs"},{"original":"וּ/מֵ֥אָה","translit":"u./Me.'ah","strongs":"H9002/{H3967}","morph":"HC/Ncfsa","gloss":"and/ one hundred"},{"original":"אֶ֖לֶף","translit":"'E.lef","strongs":"{H0505G}","morph":"HNcbsa","gloss":"thousand"},{"original":"אֵילִ֥ים","translit":"'ei.Lim","strongs":"{H0352A}","morph":"HNcmpa","gloss":"rams"},{"original":"צָֽמֶר\\׃","translit":"Tza.mer","strongs":"{H6785}\\H9016","morph":"HNcmsa","gloss":"wool"}]}