{"ref":"Psa.74.6","book":"PSA","chapter":"74","verse":"6","testament":"OT","words":[{"original":"וְ֭/עַתָּה","translit":"Ve./'a.tah","strongs":"H9002/{H6258}","morph":"HC/D","gloss":"and/ now"},{"original":"פִּתּוּחֶ֣י/הָ","translit":"pi.tu.Chei./ha","strongs":"{H6603}/H9024","morph":"HNcmpc/Sp3fs","gloss":"engravings/ its"},{"original":"יָּ֑חַד","translit":"Ya.chad","strongs":"{H3162A}","morph":"HNcmsa","gloss":"altogether"},{"original":"בְּ/כַשִּׁ֥יל","translit":"be./kha.Shil","strongs":"H9003/{H3781}","morph":"HR/Ncmsa","gloss":"with/ axe[s]"},{"original":"וְ֝/כֵֽילַפֹּ֗ת","translit":"ve./khei.la.Pot","strongs":"H9002/{H3597}","morph":"HC/Ncfpa","gloss":"and/ crowbars"},{"original":"יַהֲלֹמֽוּ/ן\\׃","translit":"ya.ha.lo.Mu/n","strongs":"{H1986}/H9013\\H9016","morph":"HVqi3mp/Sn","gloss":"they struck/ !"}]}