{"ref":"Psa.69.13","book":"PSA","chapter":"69","verse":"13","testament":"OT","words":[{"original":"וַ/אֲנִ֤י","translit":"va./'a.Ni","strongs":"H9002/{H0589}","morph":"HC/Pp1bs","gloss":"and/ I"},{"original":"תְפִלָּתִֽ/י\\־","translit":"te.fi.la.t/i-","strongs":"{H8605}/H9020\\H9014","morph":"HNcfsc/Sp1bs","gloss":"prayer/ my"},{"original":"לְ/ךָ֨\\׀","translit":"le./Kha","strongs":"H9005/{H9031}\\H9015","morph":"HR/Sp2ms","gloss":"[is] to/ you"},{"original":"יְהוָ֡ה","translit":"Yah.weh","strongs":"{H3068G}","morph":"HNpt","gloss":"O Yahweh"},{"original":"עֵ֤ת","translit":"'et","strongs":"{H6256}","morph":"HNcbsc","gloss":"a time of"},{"original":"רָצ֗וֹן","translit":"ra.Tzon","strongs":"{H7522}","morph":"HNcmsa","gloss":"favor"},{"original":"אֱלֹהִ֥ים","translit":"'E.lo.Him","strongs":"{H0430G}","morph":"HNcmpa","gloss":"O God"},{"original":"בְּ/רָב\\־","translit":"be./rov-","strongs":"H9003/{H7230}\\H9014","morph":"HR/Ncmsc","gloss":"in/ [the] greatness of"},{"original":"חַסְדֶּ֑/ךָ","translit":"chas.De./kha","strongs":"{H2617A}/H9021","morph":"HNcmsc/Sp2ms","gloss":"covenant loyalty/ your"},{"original":"עֲ֝נֵ֗/נִי","translit":"'a.Ne./ni","strongs":"{H6030B}/H9030","morph":"HVqv2ms/Sp1bs","gloss":"answer/ me"},{"original":"בֶּ/אֱמֶ֥ת","translit":"be./'e.Met","strongs":"H9003/{H0571G}","morph":"HR/Ncfsc","gloss":"in/ [the] faithfulness of"},{"original":"יִשְׁעֶֽ/ךָ\\׃","translit":"yish.'E./kha","strongs":"{H3468}/H9021\\H9016","morph":"HNcmsc/Sp2ms","gloss":"salvation/ your"}]}