{"ref":"Mrk.3.23","book":"MRK","chapter":"3","verse":"23","testament":"NT","words":[{"original":"Καὶ","translit":"Kai","strongs":"G2532","morph":"CONJ","gloss":"And"},{"original":"προσκαλεσάμενος","translit":"proskalesamenos","strongs":"G4341","morph":"V-ADP-NSM","gloss":"having called to [Him]"},{"original":"αὐτοὺς","translit":"autous","strongs":"G0846","morph":"P-APM","gloss":"them"},{"original":"ἐν","translit":"en","strongs":"G1722","morph":"PREP","gloss":"in"},{"original":"παραβολαῖς","translit":"parabolais","strongs":"G3850","morph":"N-DPF","gloss":"parables"},{"original":"ἔλεγεν","translit":"elegen","strongs":"G3004G","morph":"V-IAI-3S","gloss":"He was speaking"},{"original":"αὐτοῖς·","translit":"autois","strongs":"G0846","morph":"P-DPM","gloss":"to them:"},{"original":"πῶς","translit":"pōs","strongs":"G4459","morph":"PRT-I","gloss":"How"},{"original":"δύναται","translit":"dunatai","strongs":"G1410","morph":"V-PNI-3S","gloss":"is able"},{"original":"σατανᾶς","translit":"satanas","strongs":"G4567","morph":"N-NSM-T","gloss":"Satan"},{"original":"σατανᾶν","translit":"satanan","strongs":"G4567","morph":"N-ASM-T","gloss":"Satan"},{"original":"ἐκβάλλειν;","translit":"ekballein","strongs":"G1544","morph":"V-PAN","gloss":"to cast out?"}]}