{"ref":"Hos.9.4","book":"HOS","chapter":"9","verse":"4","testament":"OT","words":[{"original":"לֹא\\־","translit":"lo'-","strongs":"{H3808}\\H9014","morph":"HTn","gloss":"not"},{"original":"יִסְּכ֨וּ","translit":"yi.se.Khu","strongs":"{H5258A}","morph":"HVqi3mp","gloss":"they will pour out"},{"original":"לַ/יהוָ֥ה\\׀","translit":"la./Yah.weh","strongs":"H9005/{H3068G}\\H9015","morph":"HR/Npt","gloss":"to/ Yahweh"},{"original":"יַיִן֮","translit":"ya.Yin","strongs":"{H3196}","morph":"HNcmsa","gloss":"wine"},{"original":"וְ/לֹ֣א","translit":"ve./Lo'","strongs":"H9002/{H3808}","morph":"HC/Tn","gloss":"and/ not"},{"original":"יֶֽעֶרְבוּ\\־","translit":"ye.'er.vu-","strongs":"{H6149}\\H9014","morph":"HVqi3mp","gloss":"they will be pleasing"},{"original":"ל/וֹ֒","translit":"l/o","strongs":"H9005/{H9033}","morph":"HR/Sp3ms","gloss":"to/ him"},{"original":"זִבְחֵי/הֶ֗ם","translit":"ziv.chei./Hem","strongs":"{H2077}/H9028","morph":"HNcmpc/Sp3mp","gloss":"sacrifices/ their"},{"original":"כְּ/לֶ֤חֶם","translit":"ke./Le.chem","strongs":"H9004/{H3899H}","morph":"HR/Ncmsc","gloss":"[will be] like/ bread of"},{"original":"אוֹנִים֙","translit":"'o.Nim","strongs":"{H0205H}","morph":"HNcmpa","gloss":"mourning<s>"},{"original":"לָ/הֶ֔ם","translit":"la./Hem","strongs":"H9005/{H9038}","morph":"HR/Sp3mp","gloss":"to/ them"},{"original":"כָּל\\־","translit":"kol-","strongs":"{H3605}\\H9014","morph":"HNcmsc","gloss":"all"},{"original":"אֹכְלָ֖י/ו","translit":"'o.khe.La/v","strongs":"{H0398}/H9033","morph":"HVqrmpc/Sp3ms","gloss":"[those who] eat/ it"},{"original":"יִטַמָּ֑אוּ","translit":"yi.ta.Ma.'u","strongs":"{H2930A}","morph":"HVti3mp","gloss":"they will make themselves unclean"},{"original":"כִּֽי\\־","translit":"ki-","strongs":"{H3588A}\\H9014","morph":"HTc","gloss":"for"},{"original":"לַחְמָ֣/ם","translit":"lach.Ma/m","strongs":"{H3899H}/H9028","morph":"HNcmsc/Sp3mp","gloss":"bread/ their"},{"original":"לְ/נַפְשָׁ֔/ם","translit":"le./naf.Sha/m","strongs":"H9005/{H5315L}/H9028","morph":"HR/Ncfsc/Sp3mp","gloss":"[will be] for/ self/ their"},{"original":"לֹ֥א","translit":"lo'","strongs":"{H3808}","morph":"HTn","gloss":"not"},{"original":"יָב֖וֹא","translit":"ya.Vo'","strongs":"{H0935G}","morph":"HVqi3ms","gloss":"it will go"},{"original":"בֵּ֥ית","translit":"beit","strongs":"{H1004Q}","morph":"HNcmsc","gloss":"[the] house of"},{"original":"יְהוָֽה\\׃","translit":"Yah.weh","strongs":"{H3068G}\\H9016","morph":"HNpt","gloss":"Yahweh"}]}