{"ref":"Psa.76.11","book":"PSA","chapter":"76","verse":"11","testament":"OT","words":[{"original":"נִֽדֲר֣וּ","translit":"ni.da.Ru","strongs":"{H5087}","morph":"HVqv2mp","gloss":"make vows"},{"original":"וְ/שַׁלְּמוּ֮","translit":"ve./sha.le.Mu","strongs":"H9002/{H7999A}","morph":"HC/Vpv2mp","gloss":"and/ pay [them]"},{"original":"לַ/יהוָ֪ה","translit":"la./Yah.weh","strongs":"H9005/{H3068G}","morph":"HR/Npt","gloss":"to/ Yahweh"},{"original":"אֱֽלֹהֵ֫י/כֶ֥ם","translit":"'elo.Hei./Khem","strongs":"{H0430G}/H9026","morph":"HNcmpc/Sp2mp","gloss":"God/ your"},{"original":"כָּל\\־","translit":"kol-","strongs":"{H3605}\\H9014","morph":"HNcmsc","gloss":"all"},{"original":"סְבִיבָ֑י/ו","translit":"se.vi.Va/v","strongs":"{H5439G}/H9033","morph":"HNcmpc/Sp3ms","gloss":"[those] around/ him"},{"original":"יוֹבִ֥ילוּ","translit":"yo.Vi.lu","strongs":"{H2986}","morph":"HVhi3mp","gloss":"let them bring"},{"original":"שַׁ֝֗י","translit":"shai","strongs":"{H7862}","morph":"HNcmsa","gloss":"a gift"},{"original":"לַ/מּוֹרָֽא\\׃","translit":"la./mo.Ra'","strongs":"H9005/{H4172A}\\H9016","morph":"HRd/Ncmsa","gloss":"to the/ awesome one"}]}