{"ref":"Act.23.3","book":"ACT","chapter":"23","verse":"3","testament":"NT","words":[{"original":"τότε","translit":"tote","strongs":"G5119","morph":"ADV","gloss":"Then"},{"original":"ὁ","translit":"ho","strongs":"G3588","morph":"T-NSM","gloss":"<the>"},{"original":"Παῦλος","translit":"Paulos","strongs":"G3972G","morph":"N-NSM-P","gloss":"Paul"},{"original":"πρὸς","translit":"pros","strongs":"G4314","morph":"PREP","gloss":"to"},{"original":"αὐτὸν","translit":"auton","strongs":"G0846","morph":"P-ASM","gloss":"him"},{"original":"εἶπεν·","translit":"eipen","strongs":"G2036","morph":"V-2AAI-3S","gloss":"said;"},{"original":"τύπτειν","translit":"tuptein","strongs":"G5180","morph":"V-PAN","gloss":"To strike"},{"original":"σε","translit":"se","strongs":"G4771","morph":"P-2AS","gloss":"you"},{"original":"μέλλει","translit":"mellei","strongs":"G3195","morph":"V-PAI-3S","gloss":"is about"},{"original":"ὁ","translit":"ho","strongs":"G3588","morph":"T-NSM","gloss":"<the>"},{"original":"θεός,","translit":"theos","strongs":"G2316","morph":"N-NSM-T","gloss":"God,"},{"original":"τοῖχε","translit":"toiche","strongs":"G5109","morph":"N-VSM","gloss":"wall"},{"original":"κεκονιαμένε·","translit":"kekoniamene","strongs":"G2867","morph":"V-RPP-VSM","gloss":"whitewashed!"},{"original":"καὶ","translit":"kai","strongs":"G2532","morph":"CONJ","gloss":"And"},{"original":"σὺ","translit":"su","strongs":"G4771","morph":"P-2NS","gloss":"you yourself"},{"original":"κάθῃ","translit":"kathē","strongs":"G2521","morph":"V-PNI-2S","gloss":"do you sit"},{"original":"κρίνων","translit":"krinōn","strongs":"G2919","morph":"V-PAP-NSM","gloss":"judging"},{"original":"με","translit":"me","strongs":"G3165","morph":"P-1AS","gloss":"me"},{"original":"κατὰ","translit":"kata","strongs":"G2596","morph":"PREP","gloss":"according to"},{"original":"τὸν","translit":"ton","strongs":"G3588","morph":"T-ASM","gloss":"the"},{"original":"νόμον,","translit":"nomon","strongs":"G3551","morph":"N-ASM","gloss":"law,"},{"original":"καὶ","translit":"kai","strongs":"G2532","morph":"CONJ","gloss":"and"},{"original":"παρανομῶν","translit":"paranomōn","strongs":"G3891","morph":"V-PAP-NSM","gloss":"violating law"},{"original":"κελεύεις","translit":"keleueis","strongs":"G2753","morph":"V-PAI-2S","gloss":"you command"},{"original":"με","translit":"me","strongs":"G3165","morph":"P-1AS","gloss":"me"},{"original":"τύπτεσθαι;","translit":"tuptesthai","strongs":"G5180","morph":"V-PPN","gloss":"to be struck?"}]}