{"ref":"Exo.30.31","book":"EXO","chapter":"30","verse":"31","testament":"OT","words":[{"original":"וְ/אֶל\\־","translit":"ve./'el-","strongs":"H9002/{H0413}\\H9014","morph":"HC/R","gloss":"and/ to"},{"original":"בְּנֵ֥י","translit":"be.Nei","strongs":"{H1121G}","morph":"HNcmpc","gloss":"[the] people of"},{"original":"יִשְׂרָאֵ֖ל","translit":"Yis.ra.'El","strongs":"{H3478}","morph":"HNpl","gloss":"Israel"},{"original":"תְּדַבֵּ֣ר","translit":"te.da.Ber","strongs":"{H1696G}","morph":"HVpi2ms","gloss":"you will speak"},{"original":"לֵ/אמֹ֑ר","translit":"le./Mor","strongs":"H9005/{H0559}","morph":"HR/Vqcc","gloss":"<to>/ saying"},{"original":"שֶׁ֠מֶן","translit":"She.men","strongs":"{H8081}","morph":"HNcmsc","gloss":"oil of"},{"original":"מִשְׁחַת\\־","translit":"mish.chat-","strongs":"{H4888A}\\H9014","morph":"HNcfsc","gloss":"anointing of"},{"original":"קֹ֨דֶשׁ","translit":"Ko.desh","strongs":"{H6944G}","morph":"HNcmsa","gloss":"holiness"},{"original":"יִהְיֶ֥ה","translit":"yih.Yeh","strongs":"{H1961}","morph":"HVqi3ms","gloss":"it will be"},{"original":"זֶ֛ה","translit":"zeh","strongs":"{H2088}","morph":"HTm","gloss":"this"},{"original":"לִ֖/י","translit":"l/i","strongs":"H9005/{H9030}","morph":"HRd/Sp1bs","gloss":"of/ me"},{"original":"לְ/דֹרֹתֵי/כֶֽם\\׃","translit":"le./do.ro.tei./Khem","strongs":"H9005/{H1755}/H9026\\H9016","morph":"HR/Ncfpc/Sp2mp","gloss":"to/ generations/ your"}]}