{"ref":"Mat.21.34","book":"MAT","chapter":"21","verse":"34","testament":"NT","words":[{"original":"ὅτε","translit":"hote","strongs":"G3753","morph":"CONJ","gloss":"When"},{"original":"δὲ","translit":"de","strongs":"G1161","morph":"CONJ","gloss":"then"},{"original":"ἤγγισεν","translit":"ēngisen","strongs":"G1448","morph":"V-AAI-3S","gloss":"drew near"},{"original":"ὁ","translit":"ho","strongs":"G3588","morph":"T-NSM","gloss":"the"},{"original":"καιρὸς","translit":"kairos","strongs":"G2540","morph":"N-NSM","gloss":"season"},{"original":"τῶν","translit":"tōn","strongs":"G3588","morph":"T-GPM","gloss":"of the"},{"original":"καρπῶν,","translit":"karpōn","strongs":"G2590","morph":"N-GPM","gloss":"fruits,"},{"original":"ἀπέστειλεν","translit":"apesteilen","strongs":"G0649","morph":"V-AAI-3S","gloss":"he sent"},{"original":"τοὺς","translit":"tous","strongs":"G3588","morph":"T-APM","gloss":"the"},{"original":"δούλους","translit":"doulous","strongs":"G1401","morph":"N-APM","gloss":"servants"},{"original":"αὐτοῦ","translit":"autou","strongs":"G0846","morph":"P-GSM","gloss":"of him"},{"original":"πρὸς","translit":"pros","strongs":"G4314","morph":"PREP","gloss":"to"},{"original":"τοὺς","translit":"tous","strongs":"G3588","morph":"T-APM","gloss":"the"},{"original":"γεωργοὺς","translit":"geōrgous","strongs":"G1092","morph":"N-APM","gloss":"farmers"},{"original":"λαβεῖν","translit":"labein","strongs":"G2983","morph":"V-2AAN","gloss":"to receive"},{"original":"τοὺς","translit":"tous","strongs":"G3588","morph":"T-APM","gloss":"the"},{"original":"καρποὺς","translit":"karpous","strongs":"G2590","morph":"N-APM","gloss":"fruits"},{"original":"αὐτοῦ.","translit":"autou","strongs":"G0846","morph":"P-GSM","gloss":"of him."}]}