{"ref":"Rev.16.3","book":"REV","chapter":"16","verse":"3","testament":"NT","words":[{"original":"Καὶ","translit":"Kai","strongs":"G2532","morph":"CONJ","gloss":"And"},{"original":"ὁ","translit":"ho","strongs":"G3588","morph":"T-NSM","gloss":"the"},{"original":"δεύτερος","translit":"deuteros","strongs":"G1208","morph":"A-NSM","gloss":"second"},{"original":"ἄγγελος","translit":"angelos","strongs":"G0032G","morph":"N-NSM","gloss":"angel"},{"original":"ἐξέχεεν","translit":"execheen","strongs":"G1632","morph":"V-AAI-3S","gloss":"poured out"},{"original":"τὴν","translit":"tēn","strongs":"G3588","morph":"T-ASF","gloss":"the"},{"original":"φιάλην","translit":"phialēn","strongs":"G5357","morph":"N-ASF","gloss":"bowl"},{"original":"αὐτοῦ","translit":"autou","strongs":"G0846","morph":"P-GSM","gloss":"of him"},{"original":"εἰς","translit":"eis","strongs":"G1519","morph":"PREP","gloss":"into"},{"original":"τὴν","translit":"tēn","strongs":"G3588","morph":"T-ASF","gloss":"the"},{"original":"θάλασσαν,","translit":"thalassan","strongs":"G2281","morph":"N-ASF","gloss":"sea,"},{"original":"καὶ","translit":"kai","strongs":"G2532","morph":"CONJ","gloss":"and"},{"original":"ἐγένετο","translit":"egeneto","strongs":"G1096","morph":"V-2ADI-3S","gloss":"it became"},{"original":"αἷμα","translit":"haima","strongs":"G0129G","morph":"N-NSN","gloss":"blood"},{"original":"ὡς","translit":"hōs","strongs":"G5613","morph":"PRT","gloss":"as"},{"original":"νεκροῦ,","translit":"nekrou","strongs":"G3498","morph":"A-GSM","gloss":"of [one] dead,"},{"original":"καὶ","translit":"kai","strongs":"G2532","morph":"CONJ","gloss":"and"},{"original":"πᾶσα","translit":"pasa","strongs":"G3956","morph":"A-NSF","gloss":"every"},{"original":"ψυχὴ","translit":"psuchē","strongs":"G5590K","morph":"N-NSF","gloss":"soul"},{"original":"ζωῆς","translit":"zōēs","strongs":"G2222","morph":"N-GSF","gloss":"living"},{"original":"ἀπέθανεν","translit":"apethanen","strongs":"G0599","morph":"V-2AAI-3S","gloss":"died"},{"original":"τὰ","translit":"ta","strongs":"G3588","morph":"T-NPN","gloss":"that was"},{"original":"ἐν","translit":"en","strongs":"G1722","morph":"PREP","gloss":"in"},{"original":"τῇ","translit":"tēa","strongs":"G3588","morph":"T-DSF","gloss":"the"},{"original":"θαλάσσῃ.¶","translit":"thalassē","strongs":"G2281","morph":"N-DSF","gloss":"sea."}]}