{"ref":"1Ki.18.7","book":"1KI","chapter":"18","verse":"7","testament":"OT","words":[{"original":"וַ/יְהִ֤י","translit":"va/y.Hi","strongs":"H9001/{H1961}","morph":"Hc/Vqw3ms","gloss":"and/ he was"},{"original":"עֹבַדְיָ֙הוּ֙","translit":"'oad.Ya.hu","strongs":"{H5662G}","morph":"HNpm","gloss":"Obadiah"},{"original":"בַּ/דֶּ֔רֶךְ","translit":"ba./De.rekh","strongs":"H9003/{H1870L}","morph":"HRd/Ncbsa","gloss":"on the/ way"},{"original":"וְ/הִנֵּ֥ה","translit":"ve./hi.Neh","strongs":"H9002/{H2009}","morph":"HC/Tj","gloss":"and/ there!"},{"original":"אֵלִיָּ֖הוּ","translit":"'e.li.Ya.hu","strongs":"{H0452G}","morph":"HNpm","gloss":"Elijah"},{"original":"לִ/קְרָאת֑/וֹ","translit":"li/k.ra.T/o","strongs":"H9005/{H7122G}/H9033","morph":"HR/Vqcc/Sp3ms","gloss":"to/ meet/ him"},{"original":"וַ/יַּכִּרֵ֙/הוּ֙","translit":"va/i.ya.ki.Re./hu","strongs":"H9001/{H5234A}/H9033","morph":"Hc/Vhw3ms/Sp3ms","gloss":"and/ he recognized/ him"},{"original":"וַ/יִּפֹּ֣ל","translit":"va/i.yi.Pol","strongs":"H9001/{H5307G}","morph":"Hc/Vqw3ms","gloss":"and/ he fell"},{"original":"עַל\\־","translit":"'al-","strongs":"{H5921A}\\H9014","morph":"HR","gloss":"on"},{"original":"פָּנָ֔י/ו","translit":"pa.Na/v","strongs":"{H6440H}/H9023","morph":"HNcmpc/Sp3ms","gloss":"face/ his"},{"original":"וַ/יֹּ֕אמֶר","translit":"va/i.Yo.mer","strongs":"H9001/{H0559}","morph":"Hc/Vqw3ms","gloss":"and/ he said"},{"original":"הַ/אַתָּ֥ה","translit":"ha./'a.Tah","strongs":"H9008/{H0859A}","morph":"HTi/Pp2ms","gloss":"¿/ you"},{"original":"זֶ֖ה","translit":"zeh","strongs":"{H2088}","morph":"HTm","gloss":"[is] this"},{"original":"אֲדֹנִ֥/י","translit":"'a.do.N/i","strongs":"{H0113}/H9020","morph":"HNcmsc/Sp1bs","gloss":"O lord/ my"},{"original":"אֵלִיָּֽהוּ\\׃","translit":"'e.li.Ya.hu","strongs":"{H0452G}\\H9016","morph":"HNpm","gloss":"Elijah"}]}