{"ref":"1Ki.15.30","book":"1KI","chapter":"15","verse":"30","testament":"OT","words":[{"original":"עַל\\־","translit":"'al-","strongs":"{H5921A}\\H9014","morph":"HR","gloss":"on"},{"original":"חַטֹּ֤אות","translit":"cha.Tot","strongs":"{H2403B}","morph":"HNcfpc","gloss":"[the] sins of"},{"original":"יָרָבְעָם֙","translit":"ya.ra.ve.'Am","strongs":"{H3379G}","morph":"HNpm","gloss":"Jeroboam"},{"original":"אֲשֶׁ֣ר","translit":"'a.Sher","strongs":"{H0834A}","morph":"HTr","gloss":"which"},{"original":"חָטָ֔א","translit":"cha.Ta'","strongs":"{H2398}","morph":"HVqp3ms","gloss":"he sinned"},{"original":"וַ/אֲשֶׁ֥ר","translit":"va./'a.Sher","strongs":"H9002/{H0834A}","morph":"HC/Tr","gloss":"and/ which"},{"original":"הֶחֱטִ֖יא","translit":"he.che.Ti'","strongs":"{H2398}","morph":"HVhp3ms","gloss":"he caused to sin"},{"original":"אֶת\\־","translit":"'et-","strongs":"{H0853}\\H9014","morph":"HTo","gloss":"<obj.>"},{"original":"יִשְׂרָאֵ֑ל","translit":"Yis.ra.'El","strongs":"{H3478}","morph":"HNpl","gloss":"Israel"},{"original":"בְּ/כַעְס֕/וֹ","translit":"be./kha'.S/o","strongs":"H9003/{H3708A}/H9023","morph":"HR/Ncmsc/Sp3ms","gloss":"by/ provocation/ his"},{"original":"אֲשֶׁ֣ר","translit":"'a.Sher","strongs":"{H0834A}","morph":"HTr","gloss":"which"},{"original":"הִכְעִ֔יס","translit":"hikh.'Is","strongs":"{H3707}","morph":"HVhp3ms","gloss":"he provoked to anger"},{"original":"אֶת\\־","translit":"'et-","strongs":"{H0853}\\H9014","morph":"HTo","gloss":"<obj.>"},{"original":"יְהוָ֖ה","translit":"Yah.weh","strongs":"{H3068G}","morph":"HNpt","gloss":"Yahweh"},{"original":"אֱלֹהֵ֥י","translit":"'e.lo.Hei","strongs":"{H0430G}","morph":"HNcmpc","gloss":"[the] God of"},{"original":"יִשְׂרָאֵֽל\\׃","translit":"Yis.ra.'El","strongs":"{H3478}\\H9016","morph":"HNpl","gloss":"Israel"}]}