{"ref":"Ezk.30.18","book":"EZK","chapter":"30","verse":"18","testament":"OT","words":[{"original":"וּ/בִֽ/תְחַפְנְחֵס֙","translit":"u./vi/t.chaf.ne.Ches","strongs":"H9002/H9003/{H8471}","morph":"HC/R/Npl","gloss":"and/ in/ Tahpanhes"},{"original":"חָשַׂ֣ךְ","translit":"cha.Sakh","strongs":"{H2820}","morph":"HVqp3ms","gloss":"it will withhold"},{"original":"הַ/יּ֔וֹם","translit":"hai./Yom","strongs":"H9009/{H3117G}","morph":"HTd/Ncmsa","gloss":"the/ day"},{"original":"בְּ/שִׁבְרִ/י\\־","translit":"be./shiv.r/i-","strongs":"H9003/{H7665}/H9040\\H9014","morph":"HR/Vqcc/Sp1bs","gloss":"when/ break/ I"},{"original":"שָׁם֙","translit":"sham","strongs":"{H8033G}","morph":"HD","gloss":"there"},{"original":"אֶת\\־","translit":"'et-","strongs":"{H0853}\\H9014","morph":"HTo","gloss":"<obj.>"},{"original":"מֹט֣וֹת","translit":"mo.Tot","strongs":"{H4133}","morph":"HNcfpc","gloss":"[the] yoke-bars of"},{"original":"מִצְרַ֔יִם","translit":"mitz.Ra.yim","strongs":"{H4714G}","morph":"HNpl","gloss":"Egypt"},{"original":"וְ/נִשְׁבַּת\\־","translit":"ve./nish.bat-","strongs":"H9001/{H7673A}\\H9014","morph":"Hc/VNq3ms","gloss":"and/ it will cease"},{"original":"בָּ֖/הּ","translit":"ba/h","strongs":"H9003/{H9034}","morph":"HR/Sp3fs","gloss":"in/ it"},{"original":"גְּא֣וֹן","translit":"ge.'on","strongs":"{H1347}","morph":"HNcmsc","gloss":"[the] pride of"},{"original":"עֻזָּ֑/הּ","translit":"'u.Za/h","strongs":"{H5797}/H9024","morph":"HNcmsc/Sp3fs","gloss":"strength/ its"},{"original":"הִ֚יא","translit":"hi'","strongs":"{H1931}","morph":"HPp3fs","gloss":"it"},{"original":"עָנָ֣ן","translit":"'a.Nan","strongs":"{H6051}","morph":"HNcmsa","gloss":"a cloud"},{"original":"יְכַסֶּ֔/נָּה","translit":"ye.kha.Se./nah","strongs":"{H3680}/H9034","morph":"HVpi3ms/Sp3fs","gloss":"it will cover/ it"},{"original":"וּ/בְנוֹתֶ֖י/הָ","translit":"u./ve.no.Tei./ha","strongs":"H9002/{H1323G}/H9024","morph":"HC/Ncfpc/Sp3fs","gloss":"and/ daughters/ its"},{"original":"בַּ/שְּׁבִ֥י","translit":"ba./she.Vi","strongs":"H9003/{H7628A}","morph":"HRd/Ncmsa","gloss":"in <the>/ captivity"},{"original":"תֵלַֽכְנָה\\׃","translit":"te.Lakh.nah","strongs":"{H1980G}\\H9016","morph":"HVqi3fp","gloss":"they will go"}]}