{"ref":"Jas.5.1","book":"JAS","chapter":"5","verse":"1","testament":"NT","words":[{"original":"Ἄγε","translit":"Age","strongs":"G0071","morph":"V-PAM-2S","gloss":"do come"},{"original":"νῦν","translit":"nun","strongs":"G3568","morph":"ADV","gloss":"now"},{"original":"οἱ","translit":"hoi","strongs":"G3588","morph":"T-VPM","gloss":"you who [are]"},{"original":"πλούσιοι,","translit":"plousioi","strongs":"G4145","morph":"A-VPM","gloss":"rich,"},{"original":"κλαύσατε","translit":"klausate","strongs":"G2799","morph":"V-AAM-2P","gloss":"do weep"},{"original":"ὀλολύζοντες","translit":"ololuzontes","strongs":"G3649","morph":"V-PAP-NPM","gloss":"wailing"},{"original":"ἐπὶ","translit":"epi","strongs":"G1909","morph":"PREP","gloss":"over"},{"original":"ταῖς","translit":"tais","strongs":"G3588","morph":"T-DPF","gloss":"the"},{"original":"ταλαιπωρίαις","translit":"talaipōriais","strongs":"G5004","morph":"N-DPF","gloss":"miseries"},{"original":"ὑμῶν","translit":"humōn","strongs":"G4771","morph":"P-2GP","gloss":"upon you"},{"original":"ταῖς","translit":"tais","strongs":"G3588","morph":"T-DPF","gloss":"that [are]"},{"original":"ἐπερχομέναις.","translit":"eperchomenais","strongs":"G1904","morph":"V-PNP-DPF","gloss":"coming."}]}