{"ref":"2Sa.1.17","book":"2SA","chapter":"1","verse":"17","testament":"OT","words":[{"original":"וַ/יְקֹנֵ֣ן","translit":"va/y.ko.Nen","strongs":"H9001/{H6969}","morph":"Hc/Vpw3ms","gloss":"and/ he lamented"},{"original":"דָּוִ֔ד","translit":"da.Vid","strongs":"{H1732}","morph":"HNpm","gloss":"David"},{"original":"אֶת\\־","translit":"'et-","strongs":"{H0853}\\H9014","morph":"HTo","gloss":"<obj.>"},{"original":"הַ/קִּינָ֖ה","translit":"ha./ki.Nah","strongs":"H9009/{H7015}","morph":"HTd/Ncfsa","gloss":"the/ lamentation"},{"original":"הַ/זֹּ֑את","translit":"ha./Zot","strongs":"H9009/{H2063}","morph":"HTd/Tm","gloss":"<the>/ this"},{"original":"עַל\\־","translit":"'al-","strongs":"{H5921A}\\H9014","morph":"HR","gloss":"on"},{"original":"שָׁא֖וּל","translit":"sha.'Ul","strongs":"{H7586G}","morph":"HNpm","gloss":"Saul"},{"original":"וְ/עַל\\־","translit":"ve./'al-","strongs":"H9002/{H5921A}\\H9014","morph":"HC/R","gloss":"and/ on"},{"original":"יְהוֹנָתָ֥ן","translit":"ye.ho.na.Tan","strongs":"{H3083H}","morph":"HNpm","gloss":"Jonathan"},{"original":"בְּנֽ/וֹ\\׃","translit":"be.N/o","strongs":"{H1121A}/H9023\\H9016","morph":"HNcmsc/Sp3ms","gloss":"son/ his"}]}