{"strongs":"G4622","word":"Σιών","translit":"Siōn","morph":"N:N--L","gloss":"Zion","definition":"Σιών \n indecl., \n in NT anarth., but in LXX when used of the city of Jerusalem, ἡ Σ. \n (Heb. צִיּוֹן), \nZion; \n   1. the mountain: in typical sense, of the Church, Heb.12:22; of heaven, Rev.14:1. \n   2. The city, i.e. Jerusalem; in poetical sense; \n   (a) of the inhabitants: θυγάτηρ Σ, Mat.21:5, Jhn.12:15\" (LXX) ; \n   (b) in wider sense, of Israel: Rom.11:26; \n   (with) figuratively: τίθήμι ἐν Σ λίθον, Rom.9:33, 1Pe.2:6\" (LXX) .†\n (AS)","testament":"NT"}