{"ref":"1Ch.14.10","book":"1CH","chapter":"14","verse":"10","testament":"OT","words":[{"original":"וַ/יִּשְׁאַ֨ל","translit":"va/i.yish.'Al","strongs":"H9001/{H7592}","morph":"Hc/Vqw3ms","gloss":"and/ he enquired"},{"original":"דָּוִ֤יד","translit":"da.Vid","strongs":"{H1732}","morph":"HNpm","gloss":"David"},{"original":"בֵּ/אלֹהִים֙","translit":"be./lo.Him","strongs":"H9003/{H0430G}","morph":"HR/Ncmpa","gloss":"by/ God"},{"original":"לֵ/אמֹ֔ר","translit":"le./Mor","strongs":"H9005/{H0559}","morph":"HR/Vqcc","gloss":"<to>/ saying"},{"original":"הַ/אֶֽעֱלֶה֙","translit":"ha./'e.'e.Leh","strongs":"H9008/{H5927G}","morph":"HTi/Vqi1cs","gloss":"¿/ will I go up"},{"original":"עַל\\־","translit":"'al-","strongs":"{H5921A}\\H9014","morph":"HR","gloss":"on"},{"original":"פְּלִשְׁתִּ֔ים","translit":"pe.lish.ti.yim","strongs":"{H6430G}","morph":"HNgmpa","gloss":"[the] Philistines"},{"original":"וּ/נְתַתָּ֖/ם","translit":"u./ne.ta.Ta/m","strongs":"H9001/{H5414G}/H9038","morph":"Hc/Vqq2ms/Sp3mp","gloss":"and/ will you give?/ them"},{"original":"בְּ/יָדִ֑/י","translit":"be./ya.D/i","strongs":"H9003/{H3027H}/H9020","morph":"HR/Ncbsc/Sp1bs","gloss":"in/ hand/ my"},{"original":"וַ/יֹּ֨אמֶר","translit":"va/i.Yo.mer","strongs":"H9001/{H0559}","morph":"Hc/Vqw3ms","gloss":"and/ he said"},{"original":"ל֤/וֹ","translit":"l/o","strongs":"H9005/{H9033}","morph":"HR/Sp3ms","gloss":"to/ him"},{"original":"יְהוָה֙","translit":"Yah.weh","strongs":"{H3068G}","morph":"HNpt","gloss":"Yahweh"},{"original":"עֲלֵ֔ה","translit":"'a.Leh","strongs":"{H5927G}","morph":"HVqv2ms","gloss":"go up"},{"original":"וּ/נְתַתִּ֖י/ם","translit":"u./ne.ta.Ti/m","strongs":"H9001/{H5414G}/H9038","morph":"Hc/Vqq1cs/Sp3mp","gloss":"and/ I will give/ them"},{"original":"בְּ/יָדֶֽ/ךָ\\׃","translit":"be./ya.De./kha","strongs":"H9003/{H3027H}/H9021\\H9016","morph":"HR/Ncbsc/Sp2ms","gloss":"in/ hand/ your"}]}