{"ref":"Isa.49.7","book":"ISA","chapter":"49","verse":"7","testament":"OT","words":[{"original":"כֹּ֣ה","translit":"koh","strongs":"{H3541}","morph":"HD","gloss":"thus"},{"original":"אָֽמַר\\־","translit":"'a.mar-","strongs":"{H0559}\\H9014","morph":"HVqp3ms","gloss":"he says"},{"original":"יְהוָה֩","translit":"Yah.weh","strongs":"{H3068G}","morph":"HNpt","gloss":"Yahweh"},{"original":"גֹּאֵ֨ל","translit":"go.'El","strongs":"{H1350A}","morph":"HVqrmsc","gloss":"[the] redeemer of"},{"original":"יִשְׂרָאֵ֜ל","translit":"Yis.ra.'El","strongs":"{H3478}","morph":"HNpl","gloss":"Israel"},{"original":"קְדוֹשׁ֗/וֹ","translit":"ke.do.Sh/o","strongs":"{H6918G}/H9023","morph":"HAamsc/Sp3ms","gloss":"holy [one]/ its"},{"original":"לִ/בְזֹה\\־","translit":"li/v.zoh-","strongs":"H9005/{H0959}\\H9014","morph":"HR/Vqcc","gloss":"to/ despise"},{"original":"נֶ֜פֶשׁ","translit":"Ne.fesh","strongs":"{H5315J}","morph":"HNcfsa","gloss":"life"},{"original":"לִ/מְתָ֤עֵֽב","translit":"li/m.Ta.'ev","strongs":"H9005/{H8581}","morph":"HR/Vprmsc","gloss":"to/ [one who] abhors"},{"original":"גּוֹי֙","translit":"goy","strongs":"{H1471A}","morph":"HNcmsa","gloss":"<of> a nation"},{"original":"לְ/עֶ֣בֶד","translit":"le./'E.ved","strongs":"H9005/{H5650}","morph":"HR/Ncmsc","gloss":"to/ a servant of"},{"original":"מֹשְׁלִ֔ים","translit":"mo.she.Lim","strongs":"{H4910}","morph":"HVqrmpa","gloss":"rulers"},{"original":"מְלָכִים֙","translit":"me.la.Khim","strongs":"{H4428G}","morph":"HNcmpa","gloss":"kings"},{"original":"יִרְא֣וּ","translit":"yir.'U","strongs":"{H7200G}","morph":"HVqi3mp","gloss":"they will see"},{"original":"וָ/קָ֔מוּ","translit":"va./Ka.mu","strongs":"H9001/{H6965B}","morph":"Hc/Vqq3cp","gloss":"and/ they will stand up"},{"original":"שָׂרִ֖ים","translit":"sa.Rim","strongs":"{H8269}","morph":"HNcmpa","gloss":"princes"},{"original":"וְ/יִֽשְׁתַּחֲוּ֑וּ","translit":"ve./yish.ta.cha.Vu","strongs":"H9002/{H7812}","morph":"HC/Vvu3mp","gloss":"so/ they may bow down"},{"original":"לְמַ֤עַן","translit":"le.Ma.'an","strongs":"{H4616}","morph":"HTc","gloss":"on account of"},{"original":"יְהוָה֙","translit":"Yah.weh","strongs":"{H3068G}","morph":"HNpt","gloss":"Yahweh"},{"original":"אֲשֶׁ֣ר","translit":"'a.Sher","strongs":"{H0834A}","morph":"HTr","gloss":"who"},{"original":"נֶאֱמָ֔ן","translit":"ne.'e.Man","strongs":"{H0539}","morph":"HVNrmsa","gloss":"[is] faithful"},{"original":"קְדֹ֥שׁ","translit":"ke.Dosh","strongs":"{H6918G}","morph":"HAamsc","gloss":"[the] holy [one] of"},{"original":"יִשְׂרָאֵ֖ל","translit":"Yis.ra.'El","strongs":"{H3478}","morph":"HNpl","gloss":"Israel"},{"original":"וַ/יִּבְחָרֶֽ/ךָּ\\׃","translit":"va/i.yiv.cha.Re./ka","strongs":"H9001/{H0977}/H9031\\H9016","morph":"Hc/Vqw3ms/Sp2ms","gloss":"and/ he has chosen/ you"}]}