{"ref":"Psa.18.48","book":"PSA","chapter":"18","verse":"48","testament":"OT","words":[{"original":"מְפַלְּטִ֗/י","translit":"me.fa.le.T/i","strongs":"{H6403}/H9030","morph":"HVprmsc/Sp1bs","gloss":"[he has] delivered/ me"},{"original":"מֵ/אֹ֫יְבָ֥/י","translit":"me./'O.ye.Va/i","strongs":"H9006/{H0341}/H9020","morph":"HR/Vqrmpc/Sp1bs","gloss":"from/ enemies/ my"},{"original":"אַ֣ף","translit":"'af","strongs":"{H0637}","morph":"HTj","gloss":"also"},{"original":"מִן\\־","translit":"min-","strongs":"{H4480A}\\H9014","morph":"HR","gloss":"more than"},{"original":"קָ֭מַ/י","translit":"Ka.ma/i","strongs":"{H6965B}/H9030","morph":"HVqrmpc/Sp1bs","gloss":"[those who] rose against/ me"},{"original":"תְּרוֹמְמֵ֑/נִי","translit":"te.ro.Me./ni","strongs":"{H7311A}/H9030","morph":"HVpi2ms/Sp1bs","gloss":"you have exalted/ me"},{"original":"מֵ/אִ֥ישׁ","translit":"me./'Ish","strongs":"H9006/{H0376G}","morph":"HR/Ncmsc","gloss":"from/ a man of"},{"original":"חָ֝מָ֗ס","translit":"cha.Mas","strongs":"{H2555}","morph":"HNcmsa","gloss":"violence"},{"original":"תַּצִּילֵֽ/נִי\\׃","translit":"ta.tzi.Le./ni","strongs":"{H5337}/H9030\\H9016","morph":"HVhi2ms/Sp1bs","gloss":"you have rescued/ me"}]}