{"ref":"Mat.23.17","book":"MAT","chapter":"23","verse":"17","testament":"NT","words":[{"original":"μωροὶ","translit":"mōroi","strongs":"G3474","morph":"A-VPM","gloss":"Foolish"},{"original":"καὶ","translit":"kai","strongs":"G2532","morph":"CONJ","gloss":"and"},{"original":"τυφλοί,","translit":"tuphloi","strongs":"G5185","morph":"A-VPM","gloss":"blind!"},{"original":"τίς","translit":"tis","strongs":"G5101","morph":"I-NSM","gloss":"Which"},{"original":"γὰρ","translit":"gar","strongs":"G1063","morph":"CONJ","gloss":"for"},{"original":"μείζων","translit":"meizōn","strongs":"G3173","morph":"A-NSM-C","gloss":"greater"},{"original":"ἐστίν,","translit":"estin","strongs":"G1510","morph":"V-PAI-3S","gloss":"is,"},{"original":"ὁ","translit":"ho","strongs":"G3588","morph":"T-NSM","gloss":"the"},{"original":"χρυσὸς","translit":"chrusos","strongs":"G5557","morph":"N-NSM","gloss":"gold"},{"original":"ἢ","translit":"ē","strongs":"G2228","morph":"CONJ","gloss":"or"},{"original":"ὁ","translit":"ho","strongs":"G3588","morph":"T-NSM","gloss":"the"},{"original":"ναὸς","translit":"naos","strongs":"G3485","morph":"N-NSM","gloss":"temple"},{"original":"ὁ","translit":"ho","strongs":"G3588","morph":"T-NSM","gloss":"which"},{"original":"ἁγιάσας","translit":"hagiasas","strongs":"G0037","morph":"V-AAP-NSM","gloss":"is sanctifying"},{"original":"τὸν","translit":"ton","strongs":"G3588","morph":"T-ASM","gloss":"the"},{"original":"χρυσόν;","translit":"chruson","strongs":"G5557","morph":"N-ASM","gloss":"gold?"}]}