{"ref":"Luk.6.25","book":"LUK","chapter":"6","verse":"25","testament":"NT","words":[{"original":"Οὐαὶ","translit":"Ouai","strongs":"G3759","morph":"INJ","gloss":"Woe"},{"original":"ὑμῖν","translit":"humin","strongs":"G4771","morph":"P-2DP","gloss":"to you"},{"original":"οἱ","translit":"hoi","strongs":"G3588","morph":"T-VPM","gloss":"who [are]"},{"original":"ἐμπεπλησμένοι","translit":"empeplēsmenoi","strongs":"G1705","morph":"V-RPP-VPM","gloss":"filled"},{"original":"νῦν,","translit":"nun","strongs":"G3568","morph":"ADV","gloss":"now,"},{"original":"ὅτι","translit":"hoti","strongs":"G3754H","morph":"CONJ","gloss":"for"},{"original":"πεινάσετε.¶","translit":"peinasete","strongs":"G3983","morph":"V-FAI-2P","gloss":"you will hunger."},{"original":"Οὐαὶ","translit":"Ouai","strongs":"G3759","morph":"INJ","gloss":"Woe to"},{"original":"ὑμῖν","translit":"humin","strongs":"G4771","morph":"P-2DP","gloss":"to you"},{"original":"οἱ","translit":"hoi","strongs":"G3588","morph":"T-VPM","gloss":"who [are]"},{"original":"γελῶντες","translit":"gelōntes","strongs":"G1070","morph":"V-PAP-VPM","gloss":"laughing"},{"original":"νῦν,","translit":"nun","strongs":"G3568","morph":"ADV","gloss":"now,"},{"original":"ὅτι","translit":"hoti","strongs":"G3754H","morph":"CONJ","gloss":"for"},{"original":"πενθήσετε","translit":"penthēsete","strongs":"G3996","morph":"V-FAI-2P","gloss":"you will mourn"},{"original":"καὶ","translit":"kai","strongs":"G2532","morph":"CONJ","gloss":"and"},{"original":"κλαύσετε.¶","translit":"klausete","strongs":"G2799","morph":"V-FAI-2P","gloss":"will weep."}]}