{"ref":"Neh.11.30","book":"NEH","chapter":"11","verse":"30","testament":"OT","words":[{"original":"זָנֹ֤חַ","translit":"za.No.ach","strongs":"{H2182G}","morph":"HNpl","gloss":"Zanoah"},{"original":"עֲדֻלָּם֙","translit":"'a.du.Lam","strongs":"{H5725}","morph":"HNpl","gloss":"Adullam"},{"original":"וְ/חַצְרֵי/הֶ֔ם","translit":"ve./chatz.rei./Hem","strongs":"H9002/{H2691B}/H9028","morph":"HC/Ncmpc/Sp3mp","gloss":"and/ villages/ their"},{"original":"לָכִישׁ֙","translit":"la.Khish","strongs":"{H3923}","morph":"HNpl","gloss":"Lachish"},{"original":"וּ/שְׂדֹתֶ֔י/הָ","translit":"u./se.do.Tei./ha","strongs":"H9002/{H7704G}/H9024","morph":"HC/Ncfpc/Sp3fs","gloss":"and/ fields/ its"},{"original":"עֲזֵקָ֖ה","translit":"'a.ze.Kah","strongs":"{H5825}","morph":"HNpl","gloss":"Azekah"},{"original":"וּ/בְנֹתֶ֑י/הָ","translit":"u./ve.no.Tei./ha","strongs":"H9002/{H1323H}/H9024","morph":"HC/Ncfpc/Sp3fs","gloss":"and/ daughters/ its"},{"original":"וַ/יַּחֲנ֥וּ","translit":"va/i.ya.cha.Nu","strongs":"H9001/{H2583}","morph":"Hc/Vqw3mp","gloss":"and/ they encamped"},{"original":"מִ/בְּאֵֽר\\־","translit":"mi./be.'er-","strongs":"H9006/{H0884}+\\H9014","morph":"HR/Npl","gloss":"from/ Beer"},{"original":"שֶׁ֖בַע","translit":"She.va'","strongs":"{H0884}","morph":"HNpl","gloss":"Sheba"},{"original":"עַד\\־","translit":"'ad-","strongs":"{H5704}\\H9014","morph":"HR","gloss":"to"},{"original":"גֵּֽיא\\־","translit":"gei'-","strongs":"{H1516G}\\H9014","morph":"HNcbsc","gloss":"[the] valley of [Ben]"},{"original":"הִנֹּֽם\\׃","translit":"hi.Nom","strongs":"{H2011G}\\H9016","morph":"HNpl","gloss":"Hinnom"}]}