{"ref":"Jdg.11.16","book":"JDG","chapter":"11","verse":"16","testament":"OT","words":[{"original":"כִּ֖י","translit":"ki","strongs":"{H3588A}","morph":"HTc","gloss":"that"},{"original":"בַּ/עֲלוֹתָ֣/ם","translit":"ba./'a.lo.Ta/m","strongs":"H9003/{H5927G}/H9048","morph":"HR/Vqcc/Sp3mp","gloss":"when/ came up/ they"},{"original":"מִ/מִּצְרָ֑יִם","translit":"mi./mitz.Ra.yim","strongs":"H9006/{H4714G}","morph":"HR/Npl","gloss":"from/ Egypt"},{"original":"וַ/יֵּ֨לֶךְ","translit":"va/i.Ye.lekh","strongs":"H9001/{H1980G}","morph":"Hc/Vqw3ms","gloss":"and/ it went"},{"original":"יִשְׂרָאֵ֤ל","translit":"Yis.ra.'El","strongs":"{H3478}","morph":"HNpl","gloss":"Israel"},{"original":"בַּ/מִּדְבָּר֙","translit":"ba./mid.Bar","strongs":"H9003/{H4057B}","morph":"HRd/Ncmsa","gloss":"in the/ wilderness"},{"original":"עַד\\־","translit":"'ad-","strongs":"{H5704}\\H9014","morph":"HR","gloss":"to"},{"original":"יַם\\־","translit":"yam-","strongs":"{H3220G}\\H9014","morph":"HNcmsc","gloss":"[the] sea of"},{"original":"ס֔וּף","translit":"Suf","strongs":"{H5488G}","morph":"HNtmsa","gloss":"reed[s]"},{"original":"וַ/יָּבֹ֖א","translit":"va/i.ya.Vo'","strongs":"H9001/{H0935G}","morph":"Hc/Vqw3ms","gloss":"and/ it came"},{"original":"קָדֵֽשָׁ/ה\\׃","translit":"ka.De.sha/h","strongs":"{H6946G}/H9011\\H9016","morph":"HNpl/Sd","gloss":"Kadesh/ towards"}]}